{
  "project_info": {
    "project_number": "929613199529",
    "firebase_url": "https://gsr-finder-2-default-rtdb.asia-southeast1.firebasedatabase.app",
    "project_id": "gsr-finder-2",
    "storage_bucket": "gsr-finder-2.appspot.com"
  },
  "client": [
    {
      "client_info": {
        "mobilesdk_app_id": "1:929613199529:android:e1efb6c71f15a93ffa11b8",
        "android_client_info": {
          "package_name": "sg.edu.smu.gsrfinder"
        }
      },
      "oauth_client": [
        {
          "client_id": "929613199529-tajvguvf1fqcs6p7fsu4sq2rkuagg2td.apps.googleusercontent.com",
          "client_type": 3
        }
      ],
      "api_key": [
        {
          "current_key": "AIzaSyAlDCAfmxkC_i6CXNPlmOTt80AczwbGHWA"
        }
      ],
      "services": {
        "appinvite_service": {
          "other_platform_oauth_client": [
            {
              "client_id": "929613199529-tajvguvf1fqcs6p7fsu4sq2rkuagg2td.apps.googleusercontent.com",
              "client_type": 3
            }
          ]
        }
      }
    }
  ],
  "configuration_version": "1"
}